highyield/__init__.py
highyield/basics.py
highyield/converter.py
highyield/copy.py
highyield/create.py
highyield/ds.py
highyield/imports.py
highyield/pdf.py
highyield/rename.py
highyield/tts.py
highyield/data/RR.csv
highyield-1.1.1.dist-info/LICENSE
highyield-1.1.1.dist-info/METADATA
highyield-1.1.1.dist-info/WHEEL
highyield-1.1.1.dist-info/top_level.txt
highyield-1.1.1.dist-info/RECORD
