Metadata-Version: 2.1
Name: highyield
Version: 1.1.1
Summary: Collection of high-yield functions intended to simplify and automate specific tasks.
Home-page: https://github.com/kenf1/High-Yield
Author: KF
Author-email: kenfv1@outlook.com
License: GPLv3
Classifier: Programming Language :: Python :: 3
Classifier: License :: OSI Approved :: GNU General Public License v3 (GPLv3)
Classifier: Operating System :: OS Independent
Requires-Python: >=3.8
License-File: LICENSE
Requires-Dist: pandas
Requires-Dist: seaborn
Requires-Dist: pyttsx3
Requires-Dist: docx2pdf
Requires-Dist: pypdf
Requires-Dist: requests
